tests
wavchunk
