Metadata-Version: 2.1
Name: wavchunk
Version: 1.0.1
Summary: Read or write INFO chunks in WAV files
Home-page: https://github.com/synesthesiam/wav-chunk
Author: Michael Hansen
Author-email: mike@rhasspy.org
License: UNKNOWN
Platform: UNKNOWN
Classifier: Programming Language :: Python :: 3
Classifier: Programming Language :: Python :: 3.6
Classifier: Programming Language :: Python :: 3.7
Classifier: Programming Language :: Python :: 3.8
Classifier: License :: OSI Approved :: MIT License
Requires-Python: >=3.6
